comfig/__init__.py
comfig/cli.py
comfig/manager.py
comfig-0.2.2.dist-info/LICENSE
comfig-0.2.2.dist-info/WHEEL
comfig-0.2.2.dist-info/METADATA
comfig-0.2.2.dist-info/RECORD
