Metadata-Version: 2.1
Name: comfig
Version: 0.2.2
Summary: 
License: MIT
Author: Stanislav Zmiev
Author-email: szmiev2000@gmail.com
Requires-Python: >=3.8,<4.0
Classifier: License :: OSI Approved :: MIT License
Classifier: Programming Language :: Python :: 3
Classifier: Programming Language :: Python :: 3.10
Classifier: Programming Language :: Python :: 3.8
Classifier: Programming Language :: Python :: 3.9
Requires-Dist: typer (>=0.6.1,<0.7.0)
